apebench/__init__.py
apebench/__main__.py
apebench/_base_scenario.py
apebench/_cli.py
apebench/_corrected_stepper.py
apebench/_run.py
apebench/_scraper.py
apebench/_utils.py
apebench/components/__init__.py
apebench/components/_activation_function.py
apebench/components/_architectures.py
apebench/components/_initial_condition.py
apebench/components/_metrics.py
apebench/components/_optimization.py
apebench/scenarios/__init__.py
apebench/scenarios/difficulty/__init__.py
apebench/scenarios/difficulty/_convection.py
apebench/scenarios/difficulty/_linear.py
apebench/scenarios/difficulty/_nonlinear.py
apebench/scenarios/normalized/__init__.py
apebench/scenarios/normalized/_convection.py
apebench/scenarios/normalized/_linear.py
apebench/scenarios/normalized/_nonlinear.py
apebench/scenarios/physical/__init__.py
apebench/scenarios/physical/_convection.py
apebench/scenarios/physical/_gray_scott.py
apebench/scenarios/physical/_linear.py
apebench/scenarios/physical/_navier_stokes.py
apebench/scenarios/physical/_nonlinear.py
apebench/scenarios/physical/_poisson.py
apebench/scenarios/physical/_polynomial.py
apebench/scenarios/physical/_special_linear.py
apebench/scenarios/physical/_swift_hohenberg.py
apebench-0.1.1.dist-info/LICENSE.txt
apebench-0.1.1.dist-info/METADATA
apebench-0.1.1.dist-info/WHEEL
apebench-0.1.1.dist-info/entry_points.txt
apebench-0.1.1.dist-info/top_level.txt
apebench-0.1.1.dist-info/RECORD
