Metadata-Version: 2.1
Name: apebench
Version: 0.1.1
Summary: Benchmark suite for Autoregressive Neural Emulators of PDEs in JAX.
Author: Felix Koehler
Project-URL: repository, https://github.com/Ceyron/apebench
Keywords: jax,sciml,deep-learning,pde,neural operator
Requires-Python: ~=3.10
License-File: LICENSE.txt
Requires-Dist: jax >=0.4.13
Requires-Dist: jaxtyping >=0.2.20
Requires-Dist: typing-extensions >=4.5.0
Requires-Dist: equinox >=0.11.3
Requires-Dist: optax >=0.2.0
Requires-Dist: tqdm >=4.63.2
Requires-Dist: matplotlib >=3.8.1
Requires-Dist: pandas >=2.2.0
Requires-Dist: seaborn >=0.13.0
Requires-Dist: exponax ==0.1.0
Requires-Dist: pdequinox ==0.1.2
Requires-Dist: trainax ==0.0.2
